<?xml version="1.0"?>
<de.ingrid.codelists.model.CodeList><id>6400</id><name>Kategorien (Open Data)</name><description/><defaultEntry>-1</defaultEntry><entries><de.ingrid.codelists.model.CodeListEntry><id>1</id><description/><localisations><de>Landwirtschaft, Fischerei, Forstwirtschaft und Nahrungsmittel</de><en>Landwirtschaft, Fischerei, Forstwirtschaft und Nahrungsmittel</en></localisations><data>AGRI</data><fields><de>Landwirtschaft, Fischerei, Forstwirtschaft und Nahrungsmittel</de><en>Landwirtschaft, Fischerei, Forstwirtschaft und Nahrungsmittel</en></fields></de.ingrid.codelists.model.CodeListEntry><de.ingrid.codelists.model.CodeListEntry><id>2</id><description/><localisations><de>Wirtschaft und Finanzen</de><en>Wirtschaft und Finanzen</en></localisations><data>ECON</data><fields><de>Wirtschaft und Finanzen</de><en>Wirtschaft und Finanzen</en></fields></de.ingrid.codelists.model.CodeListEntry><de.ingrid.codelists.model.CodeListEntry><id>3</id><description/><localisations><de>Bildung, Kultur und Sport</de><en>Bildung, Kultur und Sport</en></localisations><data>EDUC</data><fields><de>Bildung, Kultur und Sport</de><en>Bildung, Kultur und Sport</en></fields></de.ingrid.codelists.model.CodeListEntry><de.ingrid.codelists.model.CodeListEntry><id>4</id><description/><localisations><de>Energie</de><en>Energie</en></localisations><data>ENER</data><fields><de>Energie</de><en>Energie</en></fields></de.ingrid.codelists.model.CodeListEntry><de.ingrid.codelists.model.CodeListEntry><id>5</id><description/><localisations><de>Umwelt</de><en>Umwelt</en></localisations><data>ENVI</data><fields><de>Umwelt</de><en>Umwelt</en></fields></de.ingrid.codelists.model.CodeListEntry><de.ingrid.codelists.model.CodeListEntry><id>6</id><description/><localisations><de>Gesundheit</de><en>Gesundheit</en></localisations><data>HEAL</data><fields><de>Gesundheit</de><en>Gesundheit</en></fields></de.ingrid.codelists.model.CodeListEntry><de.ingrid.codelists.model.CodeListEntry><id>7</id><description/><localisations><de>Internationale Themen</de><en>Internationale Themen</en></localisations><data>INTR</data><fields><de>Internationale Themen</de><en>Internationale Themen</en></fields></de.ingrid.codelists.model.CodeListEntry><de.ingrid.codelists.model.CodeListEntry><id>8</id><description/><localisations><de>Justiz, Rechtssystem und &#xF6;ffentliche Sicherheit</de><en>Justiz, Rechtssystem und &#xF6;ffentliche Sicherheit</en></localisations><data>JUST</data><fields><de>Justiz, Rechtssystem und &#xF6;ffentliche Sicherheit</de><en>Justiz, Rechtssystem und &#xF6;ffentliche Sicherheit</en></fields></de.ingrid.codelists.model.CodeListEntry><de.ingrid.codelists.model.CodeListEntry><id>9</id><description/><localisations><de>Bev&#xF6;lkerung und Gesellschaft</de><en>Bev&#xF6;lkerung und Gesellschaft</en></localisations><data>SOCI</data><fields><de>Bev&#xF6;lkerung und Gesellschaft</de><en>Bev&#xF6;lkerung und Gesellschaft</en></fields></de.ingrid.codelists.model.CodeListEntry><de.ingrid.codelists.model.CodeListEntry><id>10</id><description/><localisations><de>Regierung und &#xF6;ffentlicher Sektor</de><en>Regierung und &#xF6;ffentlicher Sektor</en></localisations><data>GOVE</data><fields><de>Regierung und &#xF6;ffentlicher Sektor</de><en>Regierung und &#xF6;ffentlicher Sektor</en></fields></de.ingrid.codelists.model.CodeListEntry><de.ingrid.codelists.model.CodeListEntry><id>11</id><description/><localisations><de>Regionen und St&#xE4;dte</de><en>Regionen und St&#xE4;dte</en></localisations><data>REGI</data><fields><de>Regionen und St&#xE4;dte</de><en>Regionen und St&#xE4;dte</en></fields></de.ingrid.codelists.model.CodeListEntry><de.ingrid.codelists.model.CodeListEntry><id>12</id><description/><localisations><de>Wissenschaft und Technologie</de><en>Wissenschaft und Technologie</en></localisations><data>TECH</data><fields><de>Wissenschaft und Technologie</de><en>Wissenschaft und Technologie</en></fields></de.ingrid.codelists.model.CodeListEntry><de.ingrid.codelists.model.CodeListEntry><id>13</id><description/><localisations><de>Verkehr</de><en>Verkehr</en></localisations><data>TRAN</data><fields><de>Verkehr</de><en>Verkehr</en></fields></de.ingrid.codelists.model.CodeListEntry></entries><lastModified>1720448336275</lastModified></de.ingrid.codelists.model.CodeList>
